{
    "name": "Infernal Parade",
    "type": "Ghost",
    "category": "Special",
    "basePower": 60,
    "accuracy": 100,
    "priority": 0,
    "pp": 15,
    "target": "Normal",
    "shortDesc": "Has a 30% chance to burn. Power doubled if target has status condition.",
    "isFieldMove": null,
    "smogonPage": "https://www.smogon.com/dex/ss/moves/infernal-parade",
    "serebiiPage": "https://www.serebii.net/attackdex-swsh/infernalparade.shtml",
    "bulbapediaPage": "https://bulbapedia.bulbagarden.net/wiki/Infernal_Parade_(move)"
}